[
    {
        "restaurant_name": "thanh_binh",
        "address": "17_magdalene_street_city_centre",
        "cuisine": "vietnamese",
        "price": "cheap",
        "location": "west",
        "balcony": "restaurant-with-balcony/47.png",
        "riverside": "restaurant-riverside/103.png"
    },
    {
        "restaurant_name": "zizzi_cambridge",
        "address": "47-53_regent_street",
        "cuisine": "italian",
        "price": "cheap",
        "location": "centre",
        "rooftop": "restaurant-rooftop/280.png",
        "private_room": "restaurant-with-private-room/118.png"
    },
    {
        "restaurant_name": "the_gandhi",
        "address": "72_regent_street_city_centre",
        "cuisine": "indian",
        "price": "cheap",
        "location": "centre",
        "private_room": "restaurant-with-private-room/154.png",
        "dance_floor": "restaurant-with-dance-floor/63.png"
    },
    {
        "restaurant_name": "sitar_tandoori",
        "address": "43_high_street_cherry_hinton_cherry_hinton",
        "cuisine": "indian",
        "price": "expensive",
        "location": "east",
        "rooftop_bar": "restaurant-rooftop-bar/31.png",
        "private_room": "restaurant-with-private-room/44.png"
    },
    {
        "restaurant_name": "frankie_and_bennys",
        "address": "cambridge_leisure_park_clifton_way_cherry_hinton",
        "cuisine": "italian",
        "price": "expensive",
        "location": "south",
        "dining_room": "restaurant-dining-room/2.png",
        "parking_lot": "restaurant-parking-lot/1.jpg",
        "couches": "restaurant-with-couches/1.png",
        "kid_friendly": "restaurant-kid-friendly/86.png"
    },
    {
        "restaurant_name": "loch_fyne",
        "address": "the_little_rose_37_trumpington_street",
        "cuisine": "seafood",
        "price": "expensive",
        "location": "centre",
        "bar": "restaurant-with-bar/53.png",
        "couches": "restaurant-with-couches/78.png"
    },
    {
        "restaurant_name": "hk_fusion",
        "address": "21_burleigh_street_city_centre",
        "cuisine": "chinese",
        "price": "expensive",
        "location": "centre",
        "dining_room": "restaurant-dining-room/80.png",
        "rooftop": "restaurant-rooftop/165.png"
    },
    {
        "restaurant_name": "the_cambridge_chop_house",
        "address": "1_kings_parade",
        "cuisine": "british",
        "price": "expensive",
        "location": "centre",
        "kid_friendly": "restaurant-kid-friendly/108.png",
        "dance_floor": "restaurant-with-dance-floor/32.png"
    },
    {
        "restaurant_name": "jinling_noodle_bar",
        "address": "11_peas_hill_city_centre",
        "cuisine": "chinese",
        "price": "moderate",
        "location": "centre",
        "sea_view": "restaurant-with-sea-view/124.png",
        "rooftop": "restaurant-rooftop/288.png"
    },
    {
        "restaurant_name": "the_nirala",
        "address": "7_milton_road_chesterton",
        "cuisine": "indian",
        "price": "moderate",
        "location": "north",
        "garden": "restaurant-with-garden/67.png",
        "balcony": "restaurant-with-balcony/11.png"
    },
    {
        "restaurant_name": "bloomsbury_restaurant",
        "address": "crowne_plaza_hotel_20_downing_street",
        "cuisine": "international",
        "price": "moderate",
        "location": "centre",
        "private_room": "restaurant-with-private-room/172.png",
        "dining_room": "restaurant-dining-room/238.png"
    },
    {
        "restaurant_name": "the_gardenia",
        "address": "2_rose_crescent_city_centre",
        "cuisine": "mediterranean",
        "price": "cheap",
        "location": "centre",
        "kid_friendly": "restaurant-kid-friendly/77.png",
        "garden": "restaurant-with-garden/40.png"
    },
    {
        "restaurant_name": "cote",
        "address": "bridge_street_city_centre",
        "cuisine": "french",
        "price": "expensive",
        "location": "centre",
        "dance_floor": "restaurant-with-dance-floor/3.png",
        "balcony": "restaurant-with-balcony/31.png"
    },
    {
        "restaurant_name": "graffiti",
        "address": "hotel_felix_whitehouse_lane_huntingdon_road",
        "cuisine": "british",
        "price": "expensive",
        "location": "west",
        "balcony": "restaurant-with-balcony/60.png",
        "garden": "restaurant-with-garden/167.png",
        "parking_lot": "restaurant-parking-lot/12.jpg"
    },
    {
        "restaurant_name": "hotel_du_vin_and_bistro",
        "address": "15_-_19_trumpington_street",
        "cuisine": "european",
        "price": "moderate",
        "location": "centre",
        "rooftop": "restaurant-rooftop/33.png",
        "couches": "restaurant-with-couches/140.png"
    },
    {
        "restaurant_name": "maharajah_tandoori_restaurant",
        "address": "41518_castle_street_city_centre",
        "cuisine": "indian",
        "price": "expensive",
        "location": "west",
        "garden": "restaurant-with-garden/86.png",
        "kid_friendly": "restaurant-kid-friendly/103.png"
    },
    {
        "restaurant_name": "the_slug_and_lettuce",
        "address": "34_-_35_green_street",
        "cuisine": "gastropub",
        "price": "expensive",
        "location": "centre",
        "rooftop": "restaurant-rooftop/198.png",
        "dining_room": "restaurant-dining-room/234.png"
    },
    {
        "restaurant_name": "ask_restaurant",
        "address": "12_bridge_street_city_centre",
        "cuisine": "italian",
        "price": "cheap",
        "location": "centre",
        "private_room": "restaurant-with-private-room/217.png",
        "kid_friendly": "restaurant-kid-friendly/41.png"
    },
    {
        "restaurant_name": "kymmoy",
        "address": "52_mill_road_city_centre",
        "cuisine": "asian_oriental",
        "price": "expensive",
        "location": "centre",
        "rooftop_bar": "restaurant-rooftop-bar/171.png",
        "dance_floor": "restaurant-with-dance-floor/120.png"
    },
    {
        "restaurant_name": "india_house",
        "address": "31_newnham_road_newnham",
        "cuisine": "indian",
        "price": "expensive",
        "location": "west",
        "balcony": "restaurant-with-balcony/29.png",
        "dining_room": "restaurant-dining-room/342.png"
    },
    {
        "restaurant_name": "the_varsity_restaurant",
        "address": "35_saint_andrews_street_city_centre",
        "cuisine": "international",
        "price": "moderate",
        "location": "centre",
        "parking_lot": "restaurant-parking-lot/2.jpg",
        "dance_floor": "restaurant-with-dance-floor/88.png",
        "rooftop": "restaurant-rooftop/2.png"
    },
    {
        "restaurant_name": "city_stop_restaurant",
        "address": "cambridge_city_football_club_milton_road_chesterton",
        "cuisine": "european",
        "price": "expensive",
        "location": "north",
        "dining_room": "restaurant-dining-room/124.png",
        "dance_floor": "restaurant-with-dance-floor/134.png"
    },
    {
        "restaurant_name": "the_oak_bistro",
        "address": "6_lensfield_road",
        "cuisine": "british",
        "price": "moderate",
        "location": "centre",
        "bar": "restaurant-with-bar/16.png",
        "sea_view": "restaurant-with-sea-view/28.png"
    },
    {
        "restaurant_name": "yu_garden",
        "address": "529_newmarket_road_fen_ditton",
        "cuisine": "chinese",
        "price": "expensive",
        "location": "east",
        "rooftop": "restaurant-rooftop/223.png",
        "riverside": "restaurant-riverside/27.png"
    },
    {
        "restaurant_name": "rice_boat",
        "address": "37_newnham_road_newnham",
        "cuisine": "indian",
        "price": "expensive",
        "location": "west",
        "couches": "restaurant-with-couches/129.png",
        "parking_lot": "restaurant-parking-lot/3.jpg",
        "rooftop_bar": "restaurant-rooftop-bar/100.png"
    },
    {
        "restaurant_name": "dojo_noodle_bar",
        "address": "40210_millers_yard_city_centre",
        "cuisine": "asian_oriental",
        "price": "cheap",
        "location": "centre",
        "private_room": "restaurant-with-private-room/95.png",
        "balcony": "restaurant-with-balcony/24.png"
    },
    {
        "restaurant_name": "bangkok_city",
        "address": "24_green_street_city_centre",
        "cuisine": "thai",
        "price": "expensive",
        "location": "centre",
        "rooftop_bar": "restaurant-rooftop-bar/36.png",
        "bar": "restaurant-with-bar/1.png"
    },
    {
        "restaurant_name": "tandoori_palace",
        "address": "68_histon_road_chesterton",
        "cuisine": "indian",
        "price": "expensive",
        "location": "west",
        "sea_view": "restaurant-with-sea-view/114.png",
        "bar": "restaurant-with-bar/117.png"
    },
    {
        "restaurant_name": "panahar",
        "address": "8_norfolk_street_city_centre",
        "cuisine": "indian",
        "price": "expensive",
        "location": "centre",
        "rooftop_bar": "restaurant-rooftop-bar/41.png",
        "dance_floor": "restaurant-with-dance-floor/17.png"
    },
    {
        "restaurant_name": "shanghai_family_restaurant",
        "address": "39_burleigh_street_city_centre",
        "cuisine": "chinese",
        "price": "moderate",
        "location": "centre",
        "rooftop": "restaurant-rooftop/45.png",
        "bar": "restaurant-with-bar/48.png"
    },
    {
        "restaurant_name": "pizza_hut_cherry_hinton",
        "address": "g4_cambridge_leisure_park_clifton_way_cherry_hinton",
        "cuisine": "italian",
        "price": "moderate",
        "location": "south",
        "rooftop": "restaurant-rooftop/272.png",
        "bar": "restaurant-with-bar/115.png"
    },
    {
        "restaurant_name": "shiraz_restaurant",
        "address": "84_regent_street_city_centre",
        "cuisine": "mediterranean",
        "price": "expensive",
        "location": "centre",
        "private_room": "restaurant-with-private-room/298.png",
        "rooftop_bar": "restaurant-rooftop-bar/165.png"
    },
    {
        "restaurant_name": "pizza_hut_fen_ditton",
        "address": "cambridge_retail_park_newmarket_road_fen_ditton",
        "cuisine": "italian",
        "price": "moderate",
        "location": "east",
        "riverside": "restaurant-riverside/139.png",
        "garden": "restaurant-with-garden/137.png"
    },
    {
        "restaurant_name": "midsummer_house_restaurant",
        "address": "midsummer_common",
        "cuisine": "british",
        "price": "expensive",
        "location": "centre",
        "rooftop_bar": "restaurant-rooftop-bar/201.png",
        "garden": "restaurant-with-garden/44.png"
    },
    {
        "restaurant_name": "pizza_express",
        "address": "regent_street_city_centre",
        "cuisine": "italian",
        "price": "moderate",
        "location": "centre",
        "garden": "restaurant-with-garden/13.png",
        "parking_lot": "restaurant-with-parking-lot/5.jpeg",
        "sea_view": "restaurant-with-sea-view/32.png"
    },
    {
        "restaurant_name": "wagamama",
        "address": "36_saint_andrews_street",
        "cuisine": "japanese",
        "price": "expensive",
        "location": "centre",
        "garden": "restaurant-with-garden/131.png",
        "couches": "restaurant-with-couches/14.png"
    },
    {
        "restaurant_name": "la_raza",
        "address": "4_-_6_rose_crescent",
        "cuisine": "spanish",
        "price": "cheap",
        "location": "centre",
        "dining_room": "restaurant-dining-room/159.png",
        "sea_view": "restaurant-with-sea-view/41.png"
    },
    {
        "restaurant_name": "restaurant_two_two",
        "address": "22_chesterton_road_chesterton",
        "cuisine": "french",
        "price": "expensive",
        "location": "north",
        "dining_room": "restaurant-dining-room/15.png",
        "riverside": "restaurant-riverside/26.png"
    },
    {
        "restaurant_name": "kohinoor",
        "address": "74_mill_road_city_centre",
        "cuisine": "indian",
        "price": "cheap",
        "location": "centre",
        "private_room": "restaurant-with-private-room/120.png",
        "dining_room": "restaurant-dining-room/284.png"
    },
    {
        "restaurant_name": "michaelhouse_cafe",
        "address": "st._michael's_church_trinity_street_city_centre",
        "cuisine": "european",
        "price": "expensive",
        "location": "centre",
        "balcony": "restaurant-with-balcony/10.png",
        "dining_room": "restaurant-dining-room/108.png"
    },
    {
        "restaurant_name": "little_seoul",
        "address": "108_regent_street_city_centre",
        "cuisine": "korean",
        "price": "expensive",
        "location": "centre",
        "private_room": "restaurant-with-private-room/141.png",
        "kid_friendly": "restaurant-kid-friendly/118.png"
    },
    {
        "restaurant_name": "eraina",
        "address": "free_school_lane_city_centre",
        "cuisine": "european",
        "price": "expensive",
        "location": "centre",
        "private_room": "restaurant-with-private-room/239.png",
        "garden": "restaurant-with-garden/63.png"
    },
    {
        "restaurant_name": "chiquito_restaurant_bar",
        "address": "2g_cambridge_leisure_park_cherry_hinton_road_cherry_hinton",
        "cuisine": "mexican",
        "price": "expensive",
        "location": "south",
        "bar": "restaurant-with-bar/57.png",
        "private_room": "restaurant-with-private-room/255.png"
    },
    {
        "restaurant_name": "nandos_city_centre",
        "address": "33-34_saint_andrews_street",
        "cuisine": "portuguese",
        "price": "cheap",
        "location": "centre",
        "balcony": "restaurant-with-balcony/62.png",
        "dining_room": "restaurant-dining-room/107.png"
    },
    {
        "restaurant_name": "nandos",
        "address": "cambridge_leisure_park_clifton_way",
        "cuisine": "portuguese",
        "price": "cheap",
        "location": "south",
        "rooftop_bar": "restaurant-rooftop-bar/109.png",
        "sea_view": "restaurant-with-sea-view/40.png"
    },
    {
        "restaurant_name": "the_missing_sock",
        "address": "finders_corner_newmarket_road",
        "cuisine": "international",
        "price": "cheap",
        "location": "east",
        "dining_room": "restaurant-dining-room/328.png",
        "bar": "restaurant-with-bar/90.png"
    },
    {
        "restaurant_name": "hakka",
        "address": "milton_road_chesterton",
        "cuisine": "chinese",
        "price": "expensive",
        "location": "north",
        "rooftop": "restaurant-rooftop/15.png",
        "couches": "restaurant-with-couches/111.png"
    },
    {
        "restaurant_name": "anatolia",
        "address": "30_bridge_street_city_centre",
        "cuisine": "turkish",
        "price": "moderate",
        "location": "centre",
        "bar": "restaurant-with-bar/21.png",
        "garden": "restaurant-with-garden/55.png"
    },
    {
        "restaurant_name": "don_pasquale_pizzeria",
        "address": "12_market_hill_city_centre",
        "cuisine": "italian",
        "price": "expensive",
        "location": "centre",
        "kid_friendly": "restaurant-kid-friendly/74.png",
        "bar": "restaurant-with-bar/89.png"
    },
    {
        "restaurant_name": "sesame_restaurant_and_bar",
        "address": "17_hills_road_city_centre",
        "cuisine": "chinese",
        "price": "expensive",
        "location": "centre",
        "bar": "restaurant-with-bar/12.png",
        "kid_friendly": "restaurant-kid-friendly/4.png"
    },
    {
        "restaurant_name": "la_tasca",
        "address": "14_-16_bridge_street",
        "cuisine": "spanish",
        "price": "moderate",
        "location": "centre",
        "couches": "restaurant-with-couches/13.png",
        "bar": "restaurant-with-bar/116.png"
    },
    {
        "restaurant_name": "restaurant_one_seven",
        "address": "de_vere_university_arms_regent_street_city_centre",
        "cuisine": "british",
        "price": "moderate",
        "location": "centre",
        "dining_room": "restaurant-dining-room/214.png",
        "balcony": "restaurant-with-balcony/6.png",
        "parking_lot": "restaurant-parking-lot/8.jpeg"
    },
    {
        "restaurant_name": "pizza_hut_city_centre",
        "address": "regent_street_city_centre",
        "cuisine": "italian",
        "price": "cheap",
        "location": "centre",
        "bar": "restaurant-with-bar/3.png",
        "garden": "restaurant-with-garden/142.png"
    },
    {
        "restaurant_name": "charlie_chan",
        "address": "regent_street_city_centre",
        "cuisine": "chinese",
        "price": "cheap",
        "location": "centre",
        "rooftop_bar": "restaurant-rooftop-bar/76.png",
        "kid_friendly": "restaurant-kid-friendly/110.png"
    },
    {
        "restaurant_name": "cotto",
        "address": "183_east_road_city_centre",
        "cuisine": "british",
        "price": "moderate",
        "location": "centre",
        "sea_view": "restaurant-with-sea-view/117.png",
        "dining_room": "restaurant-dining-room/304.png"
    },
    {
        "restaurant_name": "j_restaurant",
        "address": "86_regent_street_city_centre",
        "cuisine": "asian_oriental",
        "price": "cheap",
        "location": "centre",
        "rooftop": "restaurant-rooftop/252.png",
        "couches": "restaurant-with-couches/124.png"
    },
    {
        "restaurant_name": "meghna",
        "address": "205_victoria_road_chesterton",
        "cuisine": "indian",
        "price": "moderate",
        "location": "west",
        "garden": "restaurant-with-garden/114.png",
        "balcony": "restaurant-with-balcony/22.png"
    },
    {
        "restaurant_name": "saigon_city",
        "address": "169_high_street_chesterton_chesterton",
        "cuisine": "asian_oriental",
        "price": "expensive",
        "location": "north",
        "dining_room": "restaurant-dining-room/323.png",
        "kid_friendly": "restaurant-kid-friendly/39.png"
    },
    {
        "restaurant_name": "fitzbillies_restaurant",
        "address": "51_trumpington_street_city_centre",
        "cuisine": "british",
        "price": "expensive",
        "location": "centre",
        "sea_view": "restaurant-with-sea-view/10.png",
        "kid_friendly": "restaurant-kid-friendly/81.png"
    },
    {
        "restaurant_name": "clowns_cafe",
        "address": "54_king_street_city_centre",
        "cuisine": "italian",
        "price": "expensive",
        "location": "centre",
        "balcony": "restaurant-with-balcony/21.png",
        "rooftop": "restaurant-rooftop/287.png"
    },
    {
        "restaurant_name": "golden_house",
        "address": "12_lensfield_road_city_centre",
        "cuisine": "chinese",
        "price": "cheap",
        "location": "centre",
        "riverside": "restaurant-riverside/20.png",
        "couches": "restaurant-with-couches/136.png"
    },
    {
        "restaurant_name": "darrys_cookhouse_and_wine_shop",
        "address": "40270_king_street_city_centre",
        "cuisine": "modern_european",
        "price": "expensive",
        "location": "centre",
        "kid_friendly": "restaurant-kid-friendly/104.png",
        "private_room": "restaurant-with-private-room/33.png"
    },
    {
        "restaurant_name": "peking_restaurant",
        "address": "10_homerton_street_city_centre",
        "cuisine": "chinese",
        "price": "expensive",
        "location": "south",
        "kid_friendly": "restaurant-kid-friendly/55.png",
        "couches": "restaurant-with-couches/35.png"
    },
    {
        "restaurant_name": "rajmahal",
        "address": "7_barnwell_road_fen_ditton",
        "cuisine": "indian",
        "price": "moderate",
        "location": "east",
        "riverside": "restaurant-riverside/41.png",
        "rooftop": "restaurant-rooftop/220.png",
        "parking_lot": "restaurant-parking-lot/10.jpeg"
    },
    {
        "restaurant_name": "curry_queen",
        "address": "106_mill_road_city_centre",
        "cuisine": "indian",
        "price": "expensive",
        "location": "centre",
        "garden": "restaurant-with-garden/92.png",
        "balcony": "restaurant-with-balcony/64.png"
    },
    {
        "restaurant_name": "royal_spice",
        "address": "victoria_avenue_chesterton",
        "cuisine": "indian",
        "price": "cheap",
        "location": "north",
        "dance_floor": "restaurant-with-dance-floor/93.png",
        "balcony": "restaurant-with-balcony/46.png"
    },
    {
        "restaurant_name": "saint_johns_chop_house",
        "address": "21_-_24_northampton_street",
        "cuisine": "british",
        "price": "moderate",
        "location": "west",
        "dining_room": "restaurant-dining-room/201.png",
        "couches": "restaurant-with-couches/54.png"
    },
    {
        "restaurant_name": "la_margherita",
        "address": "15_magdalene_street_city_centre",
        "cuisine": "italian",
        "price": "cheap",
        "location": "west",
        "couches": "restaurant-with-couches/120.png",
        "riverside": "restaurant-riverside/101.png"
    },
    {
        "restaurant_name": "curry_king",
        "address": "5_jordans_yard_bridge_street_city_centre",
        "cuisine": "indian",
        "price": "expensive",
        "location": "centre",
        "bar": "restaurant-with-bar/124.png",
        "garden": "restaurant-with-garden/50.png"
    },
    {
        "restaurant_name": "travellers_rest",
        "address": "huntingdon_road_city_centre",
        "cuisine": "british",
        "price": "expensive",
        "location": "west",
        "sea_view": "restaurant-with-sea-view/96.png",
        "dining_room": "restaurant-dining-room/285.png"
    },
    {
        "restaurant_name": "sala_thong",
        "address": "35_newnham_road_newnham",
        "cuisine": "thai",
        "price": "expensive",
        "location": "west",
        "rooftop": "restaurant-rooftop/89.png",
        "rooftop_bar": "restaurant-rooftop-bar/156.png"
    },
    {
        "restaurant_name": "the_river_bar_steakhouse_and_grill",
        "address": "quayside_off_bridge_street",
        "cuisine": "modern_european",
        "price": "cheap",
        "location": "centre",
        "couches": "restaurant-with-couches/107.png",
        "sea_view": "restaurant-with-sea-view/97.png"
    },
    {
        "restaurant_name": "the_copper_kettle",
        "address": "4_kings_parade_city_centre",
        "cuisine": "british",
        "price": "moderate",
        "location": "centre",
        "couches": "restaurant-with-couches/134.png",
        "parking_lot": "restaurant-parking-lot/9.jpeg",
        "dance_floor": "restaurant-with-dance-floor/48.png"
    },
    {
        "restaurant_name": "lan_hong_house",
        "address": "12_norfolk_street_city_centre",
        "cuisine": "chinese",
        "price": "moderate",
        "location": "centre",
        "kid_friendly": "restaurant-kid-friendly/33.png",
        "garden": "restaurant-with-garden/32.png"
    },
    {
        "restaurant_name": "backstreet_bistro",
        "address": "2_sturton_street_city_centre",
        "cuisine": "gastropub",
        "price": "expensive",
        "location": "centre",
        "rooftop": "restaurant-rooftop/24.png",
        "garden": "restaurant-with-garden/21.png"
    },
    {
        "restaurant_name": "mahal_of_cambridge",
        "address": "3_-_5_millers_yard_mill_lane",
        "cuisine": "indian",
        "price": "cheap",
        "location": "centre",
        "rooftop_bar": "restaurant-rooftop-bar/146.png",
        "rooftop": "restaurant-rooftop/29.png"
    },
    {
        "restaurant_name": "cambridge_lodge_restaurant",
        "address": "cambridge_lodge_hotel_139_huntingdon_road_city_centre",
        "cuisine": "european",
        "price": "expensive",
        "location": "west",
        "sea_view": "restaurant-with-sea-view/21.png",
        "dance_floor": "restaurant-with-dance-floor/105.png"
    },
    {
        "restaurant_name": "galleria",
        "address": "33_bridge_street",
        "cuisine": "european",
        "price": "moderate",
        "location": "centre",
        "rooftop_bar": "restaurant-rooftop-bar/30.png",
        "private_room": "restaurant-with-private-room/219.png"
    },
    {
        "restaurant_name": "pizza_express_fen_ditton",
        "address": "jesus_lane_fen_ditton",
        "cuisine": "italian",
        "price": "moderate",
        "location": "centre",
        "riverside": "restaurant-riverside/129.png",
        "dance_floor": "restaurant-with-dance-floor/78.png"
    },
    {
        "restaurant_name": "ugly_duckling",
        "address": "12_st._johns_street_city_centre",
        "cuisine": "chinese",
        "price": "expensive",
        "location": "centre",
        "sea_view": "restaurant-with-sea-view/100.png",
        "rooftop": "restaurant-rooftop/265.png"
    },
    {
        "restaurant_name": "the_good_luck_chinese_food_takeaway",
        "address": "82_cherry_hinton_road_cherry_hinton",
        "cuisine": "chinese",
        "price": "expensive",
        "location": "south",
        "riverside": "restaurant-riverside/72.png",
        "private_room": "restaurant-with-private-room/257.png"
    },
    {
        "restaurant_name": "gourmet_burger_kitchen",
        "address": "regent_street_city_centre",
        "cuisine": "north_american",
        "price": "expensive",
        "location": "centre",
        "balcony": "restaurant-with-balcony/27.png",
        "riverside": "restaurant-riverside/180.png"
    },
    {
        "restaurant_name": "meze_bar",
        "address": "196_mill_road_city_centre",
        "cuisine": "turkish",
        "price": "expensive",
        "location": "centre",
        "bar": "restaurant-with-bar/20.png",
        "dining_room": "restaurant-dining-room/98.png"
    },
    {
        "restaurant_name": "riverside_brasserie",
        "address": "doubletree_by_hilton_cambridge_granta_place_mill_lane",
        "cuisine": "modern_european",
        "price": "moderate",
        "location": "centre",
        "rooftop_bar": "restaurant-rooftop-bar/96.png",
        "dance_floor": "restaurant-with-dance-floor/6.png"
    },
    {
        "restaurant_name": "efes_restaurant",
        "address": "king_street_city_centre",
        "cuisine": "turkish",
        "price": "moderate",
        "location": "centre",
        "rooftop_bar": "restaurant-rooftop-bar/133.png",
        "balcony": "restaurant-with-balcony/42.png"
    },
    {
        "restaurant_name": "bedouin",
        "address": "100_mill_road_city_centre",
        "cuisine": "african",
        "price": "expensive",
        "location": "centre",
        "garden": "restaurant-with-garden/77.png",
        "private_room": "restaurant-with-private-room/281.png"
    },
    {
        "restaurant_name": "curry_garden",
        "address": "106_regent_street_city_centre",
        "cuisine": "indian",
        "price": "expensive",
        "location": "centre",
        "balcony": "restaurant-with-balcony/59.png",
        "garden": "restaurant-with-garden/103.png"
    },
    {
        "restaurant_name": "the_hotpot",
        "address": "66_chesterton_road_chesterton",
        "cuisine": "chinese",
        "price": "expensive",
        "location": "north",
        "rooftop_bar": "restaurant-rooftop-bar/94.png",
        "private_room": "restaurant-with-private-room/45.png"
    },
    {
        "restaurant_name": "restaurant_alimentum",
        "address": "152_-_154_hills_road",
        "cuisine": "modern_european",
        "price": "moderate",
        "location": "south",
        "dance_floor": "restaurant-with-dance-floor/121.png",
        "private_room": "restaurant-with-private-room/27.png"
    },
    {
        "restaurant_name": "curry_prince",
        "address": "451_newmarket_road_fen_ditton",
        "cuisine": "indian",
        "price": "moderate",
        "location": "east",
        "couches": "restaurant-with-couches/106.png",
        "kid_friendly": "restaurant-kid-friendly/29.png"
    },
    {
        "restaurant_name": "de_luca_cucina_and_bar",
        "address": "83_regent_street",
        "cuisine": "modern_european",
        "price": "moderate",
        "location": "centre",
        "rooftop_bar": "restaurant-rooftop-bar/134.png",
        "private_room": "restaurant-with-private-room/258.png"
    },
    {
        "restaurant_name": "stazione_restaurant_and_coffee_bar",
        "address": "market_hill_city_centre",
        "cuisine": "italian",
        "price": "expensive",
        "location": "centre",
        "private_room": "restaurant-with-private-room/247.png",
        "bar": "restaurant-with-bar/28.png"
    },
    {
        "restaurant_name": "grafton_hotel_restaurant",
        "address": "grafton_hotel_619_newmarket_road_fen_ditton",
        "cuisine": "british",
        "price": "expensive",
        "location": "east",
        "rooftop": "restaurant-rooftop/292.png",
        "garden": "restaurant-with-garden/49.png"
    },
    {
        "restaurant_name": "da_vinci_pizzeria",
        "address": "20_milton_road_chesterton",
        "cuisine": "italian",
        "price": "cheap",
        "location": "north",
        "dance_floor": "restaurant-with-dance-floor/30.png",
        "balcony": "restaurant-with-balcony/16.png"
    },
    {
        "restaurant_name": "tang_chinese",
        "address": "napier_street_city_centre",
        "cuisine": "chinese",
        "price": "expensive",
        "location": "centre",
        "bar": "restaurant-with-bar/24.png",
        "sea_view": "restaurant-with-sea-view/31.png"
    },
    {
        "restaurant_name": "rice_house",
        "address": "88_mill_road_city_centre",
        "cuisine": "chinese",
        "price": "cheap",
        "location": "centre",
        "bar": "restaurant-with-bar/104.png",
        "garden": "restaurant-with-garden/171.png"
    },
    {
        "restaurant_name": "caffe_uno",
        "address": "32_bridge_street_city_centre",
        "cuisine": "italian",
        "price": "expensive",
        "location": "centre",
        "dance_floor": "restaurant-with-dance-floor/85.png",
        "bar": "restaurant-with-bar/11.png"
    },
    {
        "restaurant_name": "ali_baba",
        "address": "59_hills_road_city_centre",
        "cuisine": "lebanese",
        "price": "moderate",
        "location": "centre",
        "sea_view": "restaurant-with-sea-view/116.png",
        "private_room": "restaurant-with-private-room/133.png"
    },
    {
        "restaurant_name": "the_golden_curry",
        "address": "mill_road_city_centre",
        "cuisine": "indian",
        "price": "expensive",
        "location": "centre",
        "kid_friendly": "restaurant-kid-friendly/63.png",
        "sea_view": "restaurant-with-sea-view/18.png"
    },
    {
        "restaurant_name": "the_cow_pizza_kitchen_and_bar",
        "address": "corn_exchange_street",
        "cuisine": "gastropub",
        "price": "moderate",
        "location": "centre",
        "private_room": "restaurant-with-private-room/62.png",
        "couches": "restaurant-with-couches/30.png"
    },
    {
        "restaurant_name": "la_mimosa",
        "address": "thompsons_lane_fen_ditton",
        "cuisine": "mediterranean",
        "price": "expensive",
        "location": "centre",
        "rooftop_bar": "restaurant-rooftop-bar/4.png",
        "dining_room": "restaurant-dining-room/77.png"
    },
    {
        "restaurant_name": "the_lucky_star",
        "address": "cambridge_leisure_park_clifton_way_cherry_hinton",
        "cuisine": "chinese",
        "price": "cheap",
        "location": "south",
        "kid_friendly": "restaurant-kid-friendly/73.png",
        "balcony": "restaurant-with-balcony/12.png"
    },
    {
        "restaurant_name": "pipasha_restaurant",
        "address": "newmarket_road_fen_ditton",
        "cuisine": "indian",
        "price": "expensive",
        "location": "east",
        "kid_friendly": "restaurant-kid-friendly/90.png",
        "private_room": "restaurant-with-private-room/75.png"
    },
    {
        "restaurant_name": "cocum",
        "address": "71_castle_street_city_centre",
        "cuisine": "indian",
        "price": "expensive",
        "location": "west",
        "couches": "restaurant-with-couches/127.png",
        "riverside": "restaurant-riverside/120.png"
    },
    {
        "restaurant_name": "prezzo",
        "address": "21_-_24_northampton_road",
        "cuisine": "italian",
        "price": "moderate",
        "location": "west",
        "rooftop": "restaurant-rooftop/6.png",
        "sea_view": "restaurant-with-sea-view/71.png"
    },
    {
        "restaurant_name": "saffron_brasserie",
        "address": "hills_road_city_centre",
        "cuisine": "indian",
        "price": "expensive",
        "location": "centre",
        "private_room": "restaurant-with-private-room/77.png",
        "couches": "restaurant-with-couches/100.png"
    },
    {
        "restaurant_name": "taj_tandoori",
        "address": "64_cherry_hinton_road_cherry_hinton",
        "cuisine": "indian",
        "price": "expensive",
        "location": "south",
        "balcony": "restaurant-with-balcony/20.png",
        "dance_floor": "restaurant-with-dance-floor/150.png"
    },
    {
        "restaurant_name": "royal_standard",
        "address": "290_mill_road_city_centre",
        "cuisine": "gastropub",
        "price": "expensive",
        "location": "east",
        "riverside": "restaurant-riverside/23.png",
        "sea_view": "restaurant-with-sea-view/134.png"
    },
    {
        "restaurant_name": "golden_wok",
        "address": "191_histon_road_chesterton",
        "cuisine": "chinese",
        "price": "moderate",
        "location": "north",
        "private_room": "restaurant-with-private-room/229.png",
        "bar": "restaurant-with-bar/79.png"
    },
    {
        "restaurant_name": "yippee_noodle_bar",
        "address": "40428_king_street_city_centre",
        "cuisine": "asian_oriental",
        "price": "moderate",
        "location": "centre",
        "riverside": "restaurant-riverside/166.png",
        "rooftop": "restaurant-rooftop/145.png"
    }
]